MANIFEST.in
README.rst
my_package.py
setup.py
sampleProject123.egg-info/PKG-INFO
sampleProject123.egg-info/SOURCES.txt
sampleProject123.egg-info/dependency_links.txt
sampleProject123.egg-info/requires.txt
sampleProject123.egg-info/top_level.txt