Metadata-Version: 1.0
Name: sampleProject123
Version: 0.1.5
Summary: A faster way to read image from bioformats
Home-page: UNKNOWN
Author: ashwinraju101
Author-email: ashwinraju101@gmail.com
License: UNKNOWN
Platform: UNKNOWN
